gabriel/Gabriel.py
gabriel/__init__.py
gabriel-1.0.5.data/scripts/gab
gabriel-1.0.5.dist-info/LICENSE
gabriel-1.0.5.dist-info/METADATA
gabriel-1.0.5.dist-info/WHEEL
gabriel-1.0.5.dist-info/top_level.txt
gabriel-1.0.5.dist-info/RECORD
