Metadata-Version: 2.1
Name: gabriel
Version: 1.0.5
Summary: Discord RPC cli tool
Home-page: https://github.com/aapriI/gabriel
Author: April
Author-email: aaprilthemonth@gmail.com
License: UNKNOWN
Platform: UNKNOWN
Classifier: Programming Language :: Python :: 3
Classifier: License :: OSI Approved :: MIT License
Classifier: Operating System :: OS Independent
